{
  "project_info": {
    "project_number": "955757030197",
    "firebase_url": "https://niujob-hackathon.firebaseio.com",
    "project_id": "niujob-hackathon",
    "storage_bucket": "niujob-hackathon.appspot.com"
  },
  "client": [
    {
      "client_info": {
        "mobilesdk_app_id": "1:955757030197:android:be8e6ed5ffd1e6e2b1ba7c",
        "android_client_info": {
          "package_name": "com.example.niu_job"
        }
      },
      "oauth_client": [
        {
          "client_id": "955757030197-ru2p5pcehbidg0iksd0gj90pt9q3vnmf.apps.googleusercontent.com",
          "client_type": 1,
          "android_info": {
            "package_name": "com.example.niu_job",
            "certificate_hash": "e4a04c07f1447f435c774575c5a94b476037821e"
          }
        },
        {
          "client_id": "955757030197-vbu9r6sl7pjoheohavi5h3vlnhd1h3jb.apps.googleusercontent.com",
          "client_type": 3
        }
      ],
      "api_key": [
        {
          "current_key": "AIzaSyB_lOERImTmdWOvBxgZ-H2p5mw1H4e444o"
        }
      ],
      "services": {
        "appinvite_service": {
          "other_platform_oauth_client": [
            {
              "client_id": "955757030197-vbu9r6sl7pjoheohavi5h3vlnhd1h3jb.apps.googleusercontent.com",
              "client_type": 3
            }
          ]
        }
      }
    }
  ],
  "configuration_version": "1"
}